{
  "user": {
    "agencyId": "",
    "avatar": "https://lh3.googleusercontent.com/a/ACg8ocJV5OxvNxun9hxLFWX9IYIW7nbI3yQ7t73rmpnl7J-F3jOSotg=s96-c",
    "bio": "Senior Live Stream Creator on Sehr Live! 🌟",
    "coins": 1000000,
    "country": "Pakistan",
    "coverPhoto": "https://images.unsplash.com/photo-1618005182384-a83a8bd57fbe?auto=format&fit=crop&w=800&q=80",
    "createdAt": "2026-07-18T08:07:59.201Z",
    "diamonds": 150,
    "dob": "",
    "email": "pardaisliveofficial@gmail.com",
    "experience": 0,
    "familyId": "",
    "fans": 0,
    "followersCount": 14203,
    "following": 0,
    "followingCount": 0,
    "fullName": "Pardais Live Official Pakistan",
    "gender": "Male",
    "hostLevel": 1,
    "isBanned": false,
    "isHost": true,
    "isVerified": false,
    "isVip": false,
    "kycStatus": "none",
    "language": "Urdu / Hinglish",
    "level": 1,
    "name": "Prince_Sehr",
    "phoneNumber": "",
    "reels": [
      {
        "location": "",
        "videoBg": "bg-gradient-to-tr from-[#ff007f] via-[#12121a] to-[#7b2cbf]",
        "liked": false,
        "caption": "#sehrlive #singing #foryou #dhamaal",
        "title": "#sehrlive #singing #foryou #dhamaal...",
        "comments": [],
        "views": "1.2K",
        "likes": 0,
        "videoUrl": "https://media.sehrlive.soulverseapps.com/reels/sehr_1001/1784808406397-f1a2fxrx.mp4",
        "song": "1000220117",
        "duration": "0:30",
        "id": "Z4gPcwHWV7Lw9Wyp3KaW"
      },
      {
        "caption": "#pakistan #pkbattle #lahore",
        "videoBg": "bg-gradient-to-tr from-[#ff007f] via-[#12121a] to-[#7b2cbf]",
        "location": "",
        "liked": false,
        "videoUrl": "https://media.sehrlive.soulverseapps.com/reels/sehr_guest_23511/1784793081584-3akfvc1t.mp4",
        "song": "1000226296",
        "duration": "0:30",
        "id": "RXiPRaCZ5pGEguVOHK7J",
        "title": "#pakistan #pkbattle #lahore...",
        "views": "1.2K",
        "comments": [],
        "likes": 0
      }
    ],
    "selectedFrameId": "vip-frame-3",
    "test_value": 1784282509030,
    "totalLikesCount": 125400,
    "twoFactorEnabled": false,
    "uid": "uHh2YY7lSFapMuIzOruhXL7T1DR2",
    "uniqueId": "sehr_1001",
    "userLevel": 1,
    "username": "pardaisliveofficial",
    "verified": true,
    "videos": [
      {
        "location": "",
        "videoBg": "bg-gradient-to-tr from-[#ff007f] via-[#12121a] to-[#7b2cbf]",
        "liked": false,
        "caption": "#sehrlive #singing #foryou #dhamaal",
        "likes": 0,
        "title": "#sehrlive #singing #foryou #dhamaal...",
        "comments": [],
        "views": "1.2K",
        "duration": "0:30",
        "id": "Z4gPcwHWV7Lw9Wyp3KaW",
        "videoUrl": "https://media.sehrlive.soulverseapps.com/reels/sehr_1001/1784808406397-f1a2fxrx.mp4",
        "song": "1000220117"
      },
      {
        "likes": 0,
        "comments": [],
        "views": "1.2K",
        "title": "#pakistan #pkbattle #lahore...",
        "duration": "0:30",
        "id": "RXiPRaCZ5pGEguVOHK7J",
        "song": "1000226296",
        "videoUrl": "https://media.sehrlive.soulverseapps.com/reels/sehr_guest_23511/1784793081584-3akfvc1t.mp4",
        "liked": false,
        "videoBg": "bg-gradient-to-tr from-[#ff007f] via-[#12121a] to-[#7b2cbf]",
        "location": "",
        "caption": "#pakistan #pkbattle #lahore"
      }
    ],
    "vipLevel": 0,
    "vipSuspended": false,
    "wealthLevel": 1,
    "xp": 0
  },
  "users": [
    {
      "dob": "",
      "hostLevel": 12,
      "language": "Urdu / Hinglish",
      "country": "Pakistan",
      "test_value": 1784282509030,
      "uniqueId": "sehr_8899",
      "phoneNumber": "",
      "wealthLevel": 34,
      "username": "Prince_Sehr",
      "userLevel": 290,
      "coverPhoto": "https://images.unsplash.com/photo-1618005182384-a83a8bd57fbe?auto=format&fit=crop&w=800&q=80",
      "level": 24,
      "gender": "Male",
      "isVerified": false,
      "coins": 1000000,
      "diamonds": 51280,
      "kycStatus": "none",
      "name": "Prince_Sehr",
      "vipLevel": 3,
      "isBanned": false,
      "familyId": "fam-kings",
      "avatar": "https://images.unsplash.com/photo-1535713875002-d1d0cf377fde?auto=format&fit=crop&w=150&h=150&q=80",
      "xp": 34960,
      "totalLikesCount": 1438828,
      "bio": "Sehr Live VIP 👑 Support is everything! Family Creator & Diamond Earner.",
      "agencyId": "agency-alpha",
      "selectedFrameId": "vip-frame-1",
      "followingCount": 280,
      "fullName": "",
      "twoFactorEnabled": true,
      "followersCount": 39370,
      "vipSuspended": false
    },
    {
      "country": "Pakistan",
      "test_value": 1784282509030,
      "uniqueId": "sehr_1001",
      "isVip": false,
      "hostLevel": 1,
      "language": "Urdu / Hinglish",
      "dob": "",
      "videos": [
        {
          "likes": 0,
          "caption": "#sehrlive #singing #foryou #dhamaal",
          "videoUrl": "https://media.sehrlive.soulverseapps.com/reels/sehr_1001/1784808406397-f1a2fxrx.mp4",
          "song": "1000220117",
          "views": "1.2K",
          "duration": "0:30",
          "id": "Z4gPcwHWV7Lw9Wyp3KaW",
          "liked": false,
          "videoBg": "bg-gradient-to-tr from-[#ff007f] via-[#12121a] to-[#7b2cbf]",
          "title": "#sehrlive #singing #foryou #dhamaal...",
          "location": "",
          "comments": []
        },
        {
          "location": "",
          "comments": [],
          "title": "#pakistan #pkbattle #lahore...",
          "liked": false,
          "videoBg": "bg-gradient-to-tr from-[#ff007f] via-[#12121a] to-[#7b2cbf]",
          "duration": "0:30",
          "id": "RXiPRaCZ5pGEguVOHK7J",
          "song": "1000226296",
          "videoUrl": "https://media.sehrlive.soulverseapps.com/reels/sehr_guest_23511/1784793081584-3akfvc1t.mp4",
          "views": "1.2K",
          "caption": "#pakistan #pkbattle #lahore",
          "likes": 0
        }
      ],
      "coins": 1000000,
      "diamonds": 0,
      "isVerified": false,
      "userLevel": 1,
      "fans": 0,
      "username": "Sehr_User",
      "coverPhoto": "https://images.unsplash.com/photo-1618005182384-a83a8bd57fbe?auto=format&fit=crop&w=800&q=80",
      "level": 1,
      "gender": "Male",
      "phoneNumber": "",
      "wealthLevel": 1,
      "avatar": "https://api.dicebear.com/7.x/adventurer/svg?seed=SaifAli%20",
      "isBanned": false,
      "familyId": "",
      "following": 0,
      "isHost": true,
      "name": "Prince_Sehr",
      "vipLevel": 0,
      "verified": true,
      "createdAt": "2026-07-18T07:54:51.211Z",
      "kycStatus": "none",
      "email": "saifkhokhar657@gmail.com",
      "uid": "z1D1gp2bDvWoV3a1iAMARoajW4J3",
      "twoFactorEnabled": false,
      "followersCount": 14228,
      "vipSuspended": false,
      "reels": [
        {
          "location": "",
          "comments": [],
          "title": "#sehrlive #singing #foryou #dhamaal...",
          "videoBg": "bg-gradient-to-tr from-[#ff007f] via-[#12121a] to-[#7b2cbf]",
          "liked": false,
          "duration": "0:30",
          "id": "Z4gPcwHWV7Lw9Wyp3KaW",
          "song": "1000220117",
          "videoUrl": "https://media.sehrlive.soulverseapps.com/reels/sehr_1001/1784808406397-f1a2fxrx.mp4",
          "views": "1.2K",
          "caption": "#sehrlive #singing #foryou #dhamaal",
          "likes": 0
        },
        {
          "location": "",
          "comments": [],
          "liked": false,
          "title": "#pakistan #pkbattle #lahore...",
          "videoBg": "bg-gradient-to-tr from-[#ff007f] via-[#12121a] to-[#7b2cbf]",
          "duration": "0:30",
          "id": "RXiPRaCZ5pGEguVOHK7J",
          "videoUrl": "https://media.sehrlive.soulverseapps.com/reels/sehr_guest_23511/1784793081584-3akfvc1t.mp4",
          "song": "1000226296",
          "views": "1.2K",
          "caption": "#pakistan #pkbattle #lahore",
          "likes": 0
        }
      ],
      "fullName": "",
      "followingCount": 0,
      "xp": 0,
      "experience": 0,
      "totalLikesCount": 125415,
      "bio": "Senior Live Stream Creator on Sehr Live! 🌟",
      "selectedFrameId": "vip-frame-1",
      "agencyId": ""
    },
    {
      "coins": 1000000,
      "diamonds": 0,
      "isVerified": true,
      "userLevel": 1,
      "username": "arooj_queen",
      "coverPhoto": "https://images.unsplash.com/photo-1618005182384-a83a8bd57fbe?auto=format&fit=crop&w=800&q=80",
      "gender": "Male",
      "phoneNumber": "",
      "wealthLevel": 1,
      "country": "Pakistan",
      "uniqueId": "sehr_1936",
      "hostLevel": 1,
      "language": "Urdu / Hinglish",
      "dob": "",
      "twoFactorEnabled": false,
      "vipSuspended": false,
      "followersCount": 0,
      "fullName": "Arooj Queen",
      "followingCount": 0,
      "xp": 0,
      "totalLikesCount": 0,
      "bio": "New Sehr Live member! Verified via Google. 🇵🇰",
      "selectedFrameId": "",
      "agencyId": "",
      "avatar": "https://api.dicebear.com/7.x/adventurer/svg?seed=Arooj%20Queen",
      "isBanned": false,
      "familyId": "",
      "vipLevel": 0,
      "kycStatus": "approved",
      "email": "arooj.queen@gmail.com"
    },
    {
      "followingCount": 0,
      "xp": 0,
      "totalLikesCount": 0,
      "bio": "Guest Explorer in Sehr Live! 🇵🇰",
      "agencyId": "",
      "selectedFrameId": "",
      "twoFactorEnabled": false,
      "vipSuspended": false,
      "followersCount": 0,
      "fullName": "Guest_14467",
      "vipLevel": 0,
      "kycStatus": "none",
      "email": "",
      "avatar": "https://images.unsplash.com/photo-1535713875002-d1d0cf377fde?auto=format&fit=crop&w=150&h=150&q=80",
      "isBanned": false,
      "familyId": "",
      "username": "guest_14467",
      "userLevel": 1,
      "coverPhoto": "https://images.unsplash.com/photo-1618005182384-a83a8bd57fbe?auto=format&fit=crop&w=800&q=80",
      "gender": "Male",
      "phoneNumber": "",
      "wealthLevel": 1,
      "coins": 1000000,
      "diamonds": 0,
      "isVerified": false,
      "dob": "",
      "country": "Pakistan",
      "uniqueId": "sehr_guest_14467",
      "hostLevel": 1,
      "language": "Urdu / Hinglish"
    },
    {
      "isBanned": false,
      "familyId": "",
      "avatar": "https://images.unsplash.com/photo-1535713875002-d1d0cf377fde?auto=format&fit=crop&w=150&h=150&q=80",
      "kycStatus": "none",
      "email": "",
      "vipLevel": 0,
      "fullName": "Guest_23511",
      "vipSuspended": false,
      "followersCount": 0,
      "twoFactorEnabled": false,
      "reels": [
        {
          "videoUrl": "https://media.sehrlive.soulverseapps.com/reels/sehr_guest_23511/1784793081584-3akfvc1t.mp4",
          "song": "1000226296",
          "views": "1.2K",
          "likes": 0,
          "caption": "#pakistan #pkbattle #lahore",
          "liked": false,
          "videoBg": "bg-gradient-to-tr from-[#ff007f] via-[#12121a] to-[#7b2cbf]",
          "title": "#pakistan #pkbattle #lahore...",
          "location": "",
          "comments": [],
          "duration": "0:30",
          "id": "RXiPRaCZ5pGEguVOHK7J"
        }
      ],
      "xp": 19,
      "agencyId": "",
      "selectedFrameId": "",
      "totalLikesCount": 0,
      "bio": "Guest Explorer in Sehr Live! 🇵🇰",
      "followingCount": 0,
      "language": "Urdu / Hinglish",
      "hostLevel": 1,
      "country": "Pakistan",
      "uniqueId": "sehr_guest_23511",
      "dob": "",
      "isVerified": false,
      "videos": [
        {
          "duration": "0:30",
          "id": "RXiPRaCZ5pGEguVOHK7J",
          "liked": false,
          "title": "#pakistan #pkbattle #lahore...",
          "videoBg": "bg-gradient-to-tr from-[#ff007f] via-[#12121a] to-[#7b2cbf]",
          "location": "",
          "comments": [],
          "likes": 0,
          "caption": "#pakistan #pkbattle #lahore",
          "videoUrl": "https://media.sehrlive.soulverseapps.com/reels/sehr_guest_23511/1784793081584-3akfvc1t.mp4",
          "song": "1000226296",
          "views": "1.2K"
        }
      ],
      "diamonds": 0,
      "coins": 1000000,
      "phoneNumber": "",
      "wealthLevel": 2,
      "coverPhoto": "https://images.unsplash.com/photo-1618005182384-a83a8bd57fbe?auto=format&fit=crop&w=800&q=80",
      "userLevel": 1,
      "username": "guest_23511",
      "gender": "Male"
    },
    {
      "phoneNumber": "",
      "wealthLevel": 1,
      "coverPhoto": "https://images.unsplash.com/photo-1618005182384-a83a8bd57fbe?auto=format&fit=crop&w=800&q=80",
      "username": "guest_247428",
      "userLevel": 1,
      "fans": 0,
      "gender": "Male",
      "level": 1,
      "isVerified": false,
      "diamonds": 0,
      "coins": 1000000,
      "dob": "",
      "isVip": false,
      "language": "Urdu / Hinglish",
      "hostLevel": 1,
      "country": "Pakistan",
      "test_value": 1784282509030,
      "uniqueId": "sehr_guest_38445",
      "experience": 0,
      "xp": 0,
      "agencyId": "",
      "selectedFrameId": "",
      "bio": "Cozy explorer observing the Sehr Live galaxy! 🌌",
      "totalLikesCount": 0,
      "followingCount": 0,
      "fullName": "Sehr Guest 247428",
      "vipSuspended": false,
      "followersCount": 0,
      "twoFactorEnabled": false,
      "createdAt": "2026-07-18T07:47:51.195Z",
      "kycStatus": "none",
      "uid": "guest_247428",
      "email": "guest_247428@sehrlive.com",
      "name": "Prince_Sehr",
      "verified": false,
      "vipLevel": 0,
      "isBanned": false,
      "familyId": "",
      "isHost": false,
      "following": 0,
      "avatar": "https://api.dicebear.com/7.x/bottts/svg?seed=guest_247428"
    },
    {
      "isVip": false,
      "language": "Urdu / Hinglish",
      "hostLevel": 1,
      "country": "Pakistan",
      "uniqueId": "sehr_guest_28397",
      "test_value": 1784282509030,
      "dob": "",
      "isVerified": false,
      "diamonds": 0,
      "coins": 1000000,
      "phoneNumber": "",
      "wealthLevel": 1,
      "coverPhoto": "https://images.unsplash.com/photo-1618005182384-a83a8bd57fbe?auto=format&fit=crop&w=800&q=80",
      "userLevel": 1,
      "username": "guest_28397",
      "fans": 0,
      "gender": "Male",
      "level": 24,
      "isBanned": false,
      "familyId": "",
      "isHost": false,
      "following": 0,
      "avatar": "https://images.unsplash.com/photo-1535713875002-d1d0cf377fde?auto=format&fit=crop&w=150&h=150&q=80",
      "createdAt": "2026-07-18T07:53:58.259Z",
      "kycStatus": "none",
      "uid": "guest_981217",
      "email": "",
      "name": "Prince_Sehr",
      "verified": false,
      "vipLevel": 0,
      "fullName": "Guest_28397",
      "followersCount": 0,
      "vipSuspended": false,
      "twoFactorEnabled": false,
      "experience": 0,
      "xp": 0,
      "selectedFrameId": "",
      "agencyId": "",
      "totalLikesCount": 0,
      "bio": "Guest Explorer in Sehr Live! 🇵🇰",
      "followingCount": 0
    },
    {
      "experience": 0,
      "bio": "Cozy explorer observing the Sehr Live galaxy! 🌌",
      "fans": 0,
      "username": "guest_326501",
      "level": 1,
      "fullName": "Sehr Guest 326501",
      "coins": 1000000,
      "diamonds": 0,
      "createdAt": "2026-07-18T07:47:47.256Z",
      "email": "guest_326501@sehrlive.com",
      "uid": "guest_326501",
      "verified": false,
      "isVip": false,
      "isHost": false,
      "following": 0,
      "country": "Pakistan",
      "avatar": "https://api.dicebear.com/7.x/bottts/svg?seed=guest_326501"
    },
    {
      "wealthLevel": 1,
      "phoneNumber": "",
      "level": 24,
      "gender": "Male",
      "userLevel": 1,
      "username": "guest_38445",
      "coverPhoto": "https://images.unsplash.com/photo-1618005182384-a83a8bd57fbe?auto=format&fit=crop&w=800&q=80",
      "isVerified": false,
      "coins": 1000000,
      "diamonds": 0,
      "dob": "",
      "hostLevel": 1,
      "language": "Urdu / Hinglish",
      "test_value": 1784282509030,
      "uniqueId": "sehr_guest_38445",
      "country": "Pakistan",
      "bio": "Guest Explorer in Sehr Live! 🇵🇰",
      "totalLikesCount": 0,
      "agencyId": "",
      "selectedFrameId": "",
      "xp": 0,
      "followingCount": 0,
      "fullName": "Guest_38445",
      "twoFactorEnabled": false,
      "followersCount": 0,
      "vipSuspended": false,
      "email": "",
      "kycStatus": "none",
      "vipLevel": 0,
      "name": "Prince_Sehr",
      "familyId": "",
      "isBanned": false,
      "avatar": "https://images.unsplash.com/photo-1535713875002-d1d0cf377fde?auto=format&fit=crop&w=150&h=150&q=80"
    },
    {
      "kycStatus": "none",
      "createdAt": "2026-07-18T07:53:58.259Z",
      "uid": "guest_981217",
      "email": "",
      "name": "Prince_Sehr",
      "vipLevel": 0,
      "verified": false,
      "isBanned": false,
      "familyId": "",
      "isHost": false,
      "following": 0,
      "avatar": "https://images.unsplash.com/photo-1535713875002-d1d0cf377fde?auto=format&fit=crop&w=150&h=150&q=80",
      "xp": 0,
      "experience": 0,
      "selectedFrameId": "",
      "agencyId": "",
      "totalLikesCount": 0,
      "bio": "Guest Explorer in Sehr Live! 🇵🇰",
      "followingCount": 0,
      "fullName": "Guest_47528",
      "vipSuspended": false,
      "followersCount": 0,
      "twoFactorEnabled": false,
      "dob": "",
      "isVip": false,
      "language": "Urdu / Hinglish",
      "hostLevel": 1,
      "country": "Pakistan",
      "test_value": 1784282509030,
      "uniqueId": "sehr_guest_47528",
      "phoneNumber": "",
      "wealthLevel": 1,
      "coverPhoto": "https://images.unsplash.com/photo-1618005182384-a83a8bd57fbe?auto=format&fit=crop&w=800&q=80",
      "username": "guest_47528",
      "fans": 0,
      "userLevel": 1,
      "gender": "Male",
      "level": 24,
      "isVerified": false,
      "diamonds": 0,
      "coins": 1000000
    },
    {
      "vipLevel": 0,
      "email": "",
      "kycStatus": "none",
      "avatar": "https://images.unsplash.com/photo-1535713875002-d1d0cf377fde?auto=format&fit=crop&w=150&h=150&q=80",
      "familyId": "",
      "isBanned": false,
      "followingCount": 0,
      "bio": "Guest Explorer in Sehr Live! 🇵🇰",
      "totalLikesCount": 0,
      "selectedFrameId": "",
      "agencyId": "",
      "xp": 0,
      "twoFactorEnabled": false,
      "vipSuspended": false,
      "followersCount": 0,
      "fullName": "Guest_54443",
      "dob": "",
      "uniqueId": "sehr_guest_54443",
      "country": "Pakistan",
      "hostLevel": 1,
      "language": "Urdu / Hinglish",
      "gender": "Male",
      "username": "guest_54443",
      "userLevel": 1,
      "coverPhoto": "https://images.unsplash.com/photo-1618005182384-a83a8bd57fbe?auto=format&fit=crop&w=800&q=80",
      "wealthLevel": 1,
      "phoneNumber": "",
      "coins": 1000000,
      "diamonds": 0,
      "isVerified": false
    },
    {
      "diamonds": 0,
      "coins": 1000000,
      "fullName": "Sehr Guest 645090",
      "fans": 0,
      "username": "guest_645090",
      "level": 1,
      "experience": 0,
      "bio": "Cozy explorer observing the Sehr Live galaxy! 🌌",
      "country": "Pakistan",
      "avatar": "https://api.dicebear.com/7.x/bottts/svg?seed=guest_645090",
      "isVip": false,
      "isHost": false,
      "following": 0,
      "verified": false,
      "createdAt": "2026-07-18T07:47:45.020Z",
      "uid": "guest_645090",
      "email": "guest_645090@sehrlive.com"
    },
    {
      "country": "Pakistan",
      "uniqueId": "sehr_guest_76509",
      "hostLevel": 1,
      "language": "Urdu / Hinglish",
      "dob": "",
      "coins": 1000000,
      "diamonds": 0,
      "isVerified": false,
      "userLevel": 1,
      "username": "guest_76509",
      "coverPhoto": "https://images.unsplash.com/photo-1618005182384-a83a8bd57fbe?auto=format&fit=crop&w=800&q=80",
      "gender": "Male",
      "phoneNumber": "",
      "wealthLevel": 1,
      "avatar": "https://images.unsplash.com/photo-1535713875002-d1d0cf377fde?auto=format&fit=crop&w=150&h=150&q=80",
      "isBanned": false,
      "familyId": "",
      "vipLevel": 0,
      "kycStatus": "none",
      "email": "",
      "twoFactorEnabled": false,
      "followersCount": 0,
      "vipSuspended": false,
      "fullName": "Guest_76509",
      "followingCount": 0,
      "xp": 0,
      "totalLikesCount": 0,
      "bio": "Guest Explorer in Sehr Live! 🇵🇰",
      "selectedFrameId": "",
      "agencyId": ""
    },
    {
      "fullName": "Sehr Guest 981217",
      "twoFactorEnabled": false,
      "followersCount": 0,
      "vipSuspended": false,
      "experience": 0,
      "xp": 0,
      "bio": "Cozy explorer observing the Sehr Live galaxy! 🌌",
      "totalLikesCount": 0,
      "agencyId": "",
      "selectedFrameId": "",
      "followingCount": 0,
      "isBanned": false,
      "following": 0,
      "isHost": false,
      "familyId": "",
      "avatar": "https://api.dicebear.com/7.x/bottts/svg?seed=guest_981217",
      "createdAt": "2026-07-18T07:53:58.259Z",
      "kycStatus": "none",
      "email": "guest_981217@sehrlive.com",
      "uid": "guest_981217",
      "name": "Prince_Sehr",
      "verified": false,
      "vipLevel": 0,
      "isVerified": false,
      "coins": 1000000,
      "diamonds": 0,
      "phoneNumber": "",
      "wealthLevel": 1,
      "username": "guest_981217",
      "userLevel": 1,
      "fans": 0,
      "coverPhoto": "https://images.unsplash.com/photo-1618005182384-a83a8bd57fbe?auto=format&fit=crop&w=800&q=80",
      "level": 1,
      "gender": "Male",
      "isVip": false,
      "hostLevel": 1,
      "language": "Urdu / Hinglish",
      "country": "Pakistan",
      "uniqueId": "sehr_guest_38445",
      "test_value": 1784282509030,
      "dob": ""
    },
    {
      "avatar": "https://lh3.googleusercontent.com/a/ACg8ocJV5OxvNxun9hxLFWX9IYIW7nbI3yQ7t73rmpnl7J-F3jOSotg=s96-c",
      "bio": "Senior Live Stream Creator on Sehr Live! 🌟",
      "coins": 1000000,
      "country": "Pakistan",
      "createdAt": "2026-07-18T08:07:59.201Z",
      "diamonds": 150,
      "email": "pardaisliveofficial@gmail.com",
      "experience": 0,
      "fans": 0,
      "following": 0,
      "fullName": "Pardais Live Official Pakistan",
      "isHost": true,
      "isVip": false,
      "level": 1,
      "uid": "uHh2YY7lSFapMuIzOruhXL7T1DR2",
      "username": "pardaisliveofficial",
      "verified": true,
      "followersCount": 14203,
      "totalLikesCount": 125400
    },
    {
      "avatar": "https://lh3.googleusercontent.com/a/ACg8ocKPOUUvibO72sYkgln3jlATL7pA5-kDrEys7hveDip5w07CDTs=s96-c",
      "bio": "Senior Live Stream Creator on Sehr Live! 🌟",
      "coins": 1000000,
      "country": "Pakistan",
      "createdAt": "2026-07-18T07:54:51.211Z",
      "diamonds": 150,
      "email": "saifkhokhar657@gmail.com",
      "experience": 0,
      "fans": 0,
      "following": 0,
      "fullName": "saif ali",
      "isHost": true,
      "isVip": false,
      "level": 1,
      "uid": "z1D1gp2bDvWoV3a1iAMARoajW4J3",
      "username": "saifkhokhar657",
      "verified": true
    },
    {
      "followersCount": 0,
      "vipSuspended": false,
      "twoFactorEnabled": false,
      "fullName": "Soul verse Official",
      "followingCount": 0,
      "selectedFrameId": "",
      "agencyId": "",
      "totalLikesCount": 0,
      "bio": "New Sehr Live member! Verified via Google. 🇵🇰",
      "xp": 0,
      "avatar": "https://lh3.googleusercontent.com/a/ACg8ocK9woxHLjd0FKpD7s88gZ8qQrjqMtHH0jsRPRo8-UNzTOwKnRQ=s96-c",
      "familyId": "",
      "isBanned": false,
      "vipLevel": 0,
      "email": "soulversepk@gmail.com",
      "kycStatus": "approved",
      "diamonds": 0,
      "coins": 1000000,
      "isVerified": true,
      "gender": "Male",
      "coverPhoto": "https://images.unsplash.com/photo-1618005182384-a83a8bd57fbe?auto=format&fit=crop&w=800&q=80",
      "userLevel": 1,
      "username": "soulversepk",
      "wealthLevel": 1,
      "phoneNumber": "",
      "uniqueId": "sehr_5237",
      "country": "Pakistan",
      "language": "Urdu / Hinglish",
      "hostLevel": 1,
      "dob": ""
    },
    {
      "isVip": false,
      "isHost": true,
      "following": 0,
      "avatar": "https://lh3.googleusercontent.com/a/ACg8ocJV5OxvNxun9hxLFWX9IYIW7nbI3yQ7t73rmpnl7J-F3jOSotg=s96-c",
      "country": "Pakistan",
      "createdAt": "2026-07-18T08:07:59.201Z",
      "uid": "uHh2YY7lSFapMuIzOruhXL7T1DR2",
      "email": "pardaisliveofficial@gmail.com",
      "verified": true,
      "fullName": "Pardais Live Official Pakistan",
      "diamonds": 150,
      "coins": 1000,
      "experience": 0,
      "bio": "Senior Live Stream Creator on Sehr Live! 🌟",
      "fans": 0,
      "username": "pardaisliveofficial",
      "level": 1
    },
    {
      "country": "Pakistan",
      "uniqueId": "sehr_8002",
      "hostLevel": 1,
      "language": "Urdu / Hinglish",
      "dob": "",
      "coins": 1000000,
      "diamonds": 0,
      "isVerified": true,
      "username": "waqasawanmalik2382",
      "userLevel": 20,
      "coverPhoto": "https://images.unsplash.com/photo-1618005182384-a83a8bd57fbe?auto=format&fit=crop&w=800&q=80",
      "gender": "Male",
      "phoneNumber": "",
      "wealthLevel": 2,
      "avatar": "https://api.dicebear.com/7.x/adventurer/svg?seed=Waqas%20Awan",
      "isBanned": false,
      "familyId": "",
      "vipLevel": 0,
      "kycStatus": "approved",
      "email": "waqasawanmalik2382@gmail.com",
      "twoFactorEnabled": false,
      "followersCount": 0,
      "vipSuspended": false,
      "fullName": "Waqas Awan",
      "followingCount": 0,
      "xp": 1998,
      "bio": "New Sehr Live member! Verified via Google. 🇵🇰",
      "totalLikesCount": 0,
      "agencyId": "",
      "selectedFrameId": ""
    },
    {
      "fullName": "saif ali",
      "diamonds": 150,
      "coins": 1000,
      "experience": 0,
      "bio": "Senior Live Stream Creator on Sehr Live! 🌟",
      "fans": 0,
      "username": "saifkhokhar657",
      "level": 1,
      "isVip": false,
      "isHost": true,
      "following": 0,
      "avatar": "https://lh3.googleusercontent.com/a/ACg8ocKPOUUvibO72sYkgln3jlATL7pA5-kDrEys7hveDip5w07CDTs=s96-c",
      "country": "Pakistan",
      "createdAt": "2026-07-18T07:54:51.211Z",
      "uid": "z1D1gp2bDvWoV3a1iAMARoajW4J3",
      "email": "saifkhokhar657@gmail.com",
      "verified": true
    }
  ],
  "gifts": [
    {
      "status": "active",
      "icon": "🏎️",
      "animationClass": "animate-bounce",
      "color": "from-blue-500 to-indigo-600",
      "id": "g-car",
      "name": "Sports Car",
      "type": "luxury",
      "cost": 4999,
      "category": "Luxury"
    },
    {
      "icon": "👑",
      "animationClass": "animate-spin",
      "status": "active",
      "name": "VIP Crown",
      "color": "from-yellow-400 to-amber-600",
      "id": "g-crown",
      "type": "3d",
      "category": "VIP",
      "cost": 999
    },
    {
      "category": "Luxury",
      "cost": 29999,
      "type": "luxury",
      "name": "Golden Dragon",
      "color": "from-amber-500 to-red-600",
      "id": "g-dragon",
      "icon": "🐉",
      "animationClass": "animate-bounce",
      "status": "active"
    },
    {
      "type": "2d",
      "category": "Popular",
      "cost": 99,
      "icon": "💖",
      "animationClass": "animate-pulse",
      "status": "active",
      "name": "Love Heart",
      "color": "from-red-500 to-pink-500",
      "id": "g-heart"
    },
    {
      "icon": "🚀",
      "animationClass": "animate-pulse",
      "status": "active",
      "name": "Space Rocket",
      "id": "g-rocket",
      "color": "from-purple-600 to-pink-600",
      "type": "luxury",
      "category": "Luxury",
      "cost": 9999
    },
    {
      "status": "active",
      "icon": "🌹",
      "animationClass": "animate-bounce",
      "color": "from-pink-500 to-rose-600",
      "id": "g-rose",
      "name": "Red Rose",
      "type": "2d",
      "cost": 10,
      "category": "Popular"
    }
  ],
  "categories": [],
  "hosts": [
    {
      "avatar": "https://lh3.googleusercontent.com/a/ACg8ocJV5OxvNxun9hxLFWX9IYIW7nbI3yQ7t73rmpnl7J-F3jOSotg=s96-c",
      "cameraEnabled": true,
      "comments": [],
      "connectedViewers": [],
      "guestModeActive": false,
      "guestSeats": [
        {
          "id": 1,
          "name": "Hamza King",
          "avatar": "https://images.unsplash.com/photo-1535713875002-d1d0cf377fde?auto=format&fit=crop&w=150&q=80",
          "diamonds": "98.2K",
          "isMuted": false,
          "isCamMuted": false,
          "isBigFrame": false
        },
        {
          "id": 2,
          "name": "Zara",
          "avatar": "https://images.unsplash.com/photo-1494790108377-be9c29b29330?auto=format&fit=crop&w=150&q=80",
          "diamonds": "76.4K",
          "isMuted": false,
          "isCamMuted": false,
          "isBigFrame": false
        },
        {
          "id": 3,
          "name": "Saad",
          "avatar": "https://images.unsplash.com/photo-1507003211169-0a1dd7228f2d?auto=format&fit=crop&w=150&q=80",
          "diamonds": "56.3K",
          "isMuted": false,
          "isCamMuted": false,
          "isBigFrame": false
        },
        {
          "id": 4,
          "name": "Noor",
          "avatar": "https://images.unsplash.com/photo-1517841905240-472988babdf9?auto=format&fit=crop&w=150&q=80",
          "diamonds": "45.6K",
          "isMuted": true,
          "isCamMuted": false,
          "isBigFrame": false
        },
        {
          "id": 5,
          "name": "Usman",
          "avatar": "https://images.unsplash.com/photo-1500648767791-00dcc994a43e?auto=format&fit=crop&w=150&q=80",
          "diamonds": "33.2K",
          "isMuted": false,
          "isCamMuted": true,
          "isBigFrame": false
        },
        {
          "id": 6,
          "name": "Hoorain",
          "avatar": "https://images.unsplash.com/photo-1534528741775-53994a69daeb?auto=format&fit=crop&w=150&q=80",
          "diamonds": "27.8K",
          "isMuted": false,
          "isCamMuted": false,
          "isBigFrame": false
        },
        {
          "id": 7,
          "name": "Ali Raza",
          "avatar": "https://images.unsplash.com/photo-1522075469751-3a6694fb2f61?auto=format&fit=crop&w=150&q=80",
          "diamonds": "21.6K",
          "isMuted": false,
          "isCamMuted": false,
          "isBigFrame": false
        },
        {
          "id": 8,
          "name": null,
          "avatar": null,
          "diamonds": null,
          "isMuted": false,
          "isCamMuted": false,
          "isBigFrame": false
        }
      ],
      "hostLevel": 1,
      "hostUsername": "pardaisliveofficial",
      "id": "h-pardaisliveofficial",
      "isCamOff": false,
      "isLive": true,
      "level": 1,
      "likes": 0,
      "name": "pardaisliveofficial",
      "pkActive": false,
      "pkScoreHost": 12560,
      "pkScoreOpponent": 9820,
      "realViewerCount": 0,
      "status": "live",
      "updatedAt": "2026-07-24T10:12:51.898Z",
      "viewers": 0,
      "vipLevel": 0,
      "agencyId": "",
      "bio": "Senior Live Stream Creator on Sehr Live! 🌟",
      "category": "video",
      "channelName": "room_pardaisliveofficial",
      "hostAvatar": "https://lh3.googleusercontent.com/a/ACg8ocJV5OxvNxun9hxLFWX9IYIW7nbI3yQ7t73rmpnl7J-F3jOSotg=s96-c",
      "hostUid": "pardaisliveofficial",
      "hostVIPStatus": "Regular",
      "liveSessionId": "session-1784887747129",
      "role": "Broadcaster",
      "startedAt": "2026-07-24T10:09:07.129Z",
      "statusText": "Sehr Live - Dynamic Jam Session 📹🎸",
      "subCategory": "Music"
    }
  ],
  "parties": [],
  "families": [
    {
      "name": "👑 SAHR KINGS",
      "leader": "Prince_Sehr",
      "members": 245,
      "rank": 1,
      "avatar": "https://images.unsplash.com/photo-1513829096999-4978602294fc?auto=format&fit=crop&w=100&h=100&q=80",
      "id": "fam-kings",
      "description": "The elite guild of premium supporters. Loyalty and respect always."
    },
    {
      "description": "Winning battles one diamond at a time! Join if you are active.",
      "leader": "Zain_Killer",
      "name": "⚡ PK WARRIORS",
      "avatar": "https://images.unsplash.com/photo-1531256379416-9f000e90aacc?auto=format&fit=crop&w=100&h=100&q=80",
      "rank": 2,
      "members": 180,
      "id": "fam-warriors"
    }
  ],
  "agencies": [
    {
      "monthlyCommission": 1250,
      "name": "Alpha Talent Agency",
      "ownerEmail": "owner@alphatalent.live",
      "salaryRate": "35% Commission + $200 Base Bonus",
      "registeredHosts": 45,
      "id": "agency-alpha"
    },
    {
      "id": "agency-delta",
      "name": "Delta Elite Entertainment",
      "ownerEmail": "delta@elite.live",
      "salaryRate": "40% Commission + $350 PK Victory Bonus",
      "registeredHosts": 32,
      "monthlyCommission": 2400
    }
  ],
  "transactions": [
    {
      "timestamp": "2026-07-15T07:40:30.305Z",
      "status": "Completed",
      "currency": "coins",
      "type": "recharge",
      "amount": 15000,
      "details": "Purchased 15k Coins via EasyPaisa",
      "id": "TXN-101"
    },
    {
      "details": "Purchased 20k Coins via JazzCash",
      "id": "TXN-102",
      "amount": 20000,
      "status": "Completed",
      "currency": "coins",
      "timestamp": "2026-07-15T04:40:30.305Z",
      "type": "recharge"
    },
    {
      "details": "Withdrawn $500 to Bank Alfalah",
      "id": "TXN-103",
      "amount": 500,
      "currency": "USD",
      "status": "Completed",
      "timestamp": "2026-07-14T09:40:30.305Z",
      "type": "withdraw"
    }
  ],
  "notifications": [],
  "reports": [
    {
      "id": "REP-401",
      "username": "toxic_viewer_9",
      "reason": "Abusive language in live chat chatroom",
      "status": "pending",
      "timestamp": "2026-07-15T09:40:30.305Z",
      "reporter": "Malik_Sheraz_40"
    },
    {
      "reporter": "Sardar_Sb_VIP",
      "timestamp": "2026-07-15T09:40:30.306Z",
      "status": "resolved",
      "username": "spammer_pak",
      "reason": "Spamming referral scam link in mic seat",
      "id": "REP-402"
    }
  ],
  "kycRequests": [
    {
      "id": "KYC-8801",
      "faceVerified": true,
      "username": "Prince_Sehr",
      "idBack": "https://images.unsplash.com/photo-1554774853-aae0a22c8aa4?auto=format&fit=crop&w=300&q=80",
      "dob": "1998-05-15",
      "status": "pending",
      "idFront": "https://images.unsplash.com/photo-1554774853-aae0a22c8aa4?auto=format&fit=crop&w=300&q=80",
      "phoneNumber": "+923001234567",
      "documentType": "id_card",
      "fullName": "Syed Prince Shah",
      "timestamp": "2026-07-15T09:40:30.306Z"
    }
  ],
  "events": [
    {
      "reward": "2x Diamonds Multiplier",
      "active": true,
      "duration": "12 Hours",
      "id": "evt-1",
      "title": "🇵🇰 Pakistan Day Mega Stream Event"
    },
    {
      "title": "🔥 PK Battle Royale Tournament",
      "reward": "Exclusive Gold Profile Frame",
      "active": true,
      "duration": "July 18 - 20",
      "id": "evt-2"
    }
  ],
  "configurations": {
    "appVersion": "v1.4.2",
    "banners": [
      {
        "active": true,
        "title": "🇵🇰 PAKISTAN DAY MEGA STREAM FESTIVAL",
        "id": "b-1",
        "link": "event-pak-day",
        "image": "https://images.unsplash.com/photo-1618005182384-a83a8bd57fbe?auto=format&fit=crop&w=800&q=80"
      },
      {
        "image": "https://images.unsplash.com/photo-1511671782779-c97d3d27a1d4?auto=format&fit=crop&w=800&q=80",
        "active": true,
        "title": "👑 SAHR TALENT RECRUITMENT PROGRAM",
        "id": "b-2",
        "link": "agency-info"
      },
      {
        "title": "⚡ OFFICIAL PK BATTLE TOURNAMENT LIVE NOW",
        "active": true,
        "id": "b-3",
        "link": "pk-tourney",
        "image": "https://images.unsplash.com/photo-1492684223066-81342ee5ff30?auto=format&fit=crop&w=800&q=80"
      }
    ],
    "coinExchangeRate": 150,
    "forceUpdate": false,
    "maintenanceDuration": "2 hours",
    "maintenanceMode": false,
    "pkSettings": {
      "allowSpectatorInterference": true,
      "defaultDuration": 180,
      "pkTappingMultiplier": 1.5
    },
    "pkrToUsd": 280,
    "vipFrames": [
      {
        "name": "Royal Bronze VIP 1",
        "gradientTo": "to-amber-500",
        "id": "vip-frame-1",
        "glowColor": "#b27a50",
        "badgeEmoji": "🥉",
        "gradientFrom": "from-amber-700",
        "minLevel": 15,
        "isActive": true
      },
      {
        "glowColor": "#94a3b8",
        "id": "vip-frame-2",
        "name": "Sky Silver Wings VIP 2",
        "gradientTo": "to-blue-300",
        "gradientFrom": "from-slate-400",
        "isActive": true,
        "minLevel": 30,
        "badgeEmoji": "🥈"
      },
      {
        "minLevel": 45,
        "isActive": true,
        "gradientFrom": "from-yellow-600",
        "badgeEmoji": "👑",
        "glowColor": "#fbbf24",
        "id": "vip-frame-3",
        "gradientTo": "to-yellow-300",
        "name": "Golden Dragon VIP 3"
      },
      {
        "glowColor": "#ef4444",
        "id": "vip-frame-4",
        "name": "Ruby Fire VIP 4",
        "gradientTo": "to-pink-500",
        "gradientFrom": "from-red-600",
        "minLevel": 60,
        "isActive": true,
        "badgeEmoji": "🔥"
      },
      {
        "name": "Celestial Diamond VIP 5",
        "gradientTo": "to-blue-400",
        "glowColor": "#06b6d4",
        "id": "vip-frame-5",
        "badgeEmoji": "💎",
        "gradientFrom": "from-cyan-500",
        "isActive": true,
        "minLevel": 75
      },
      {
        "glowColor": "#d946ef",
        "id": "vip-frame-6",
        "name": "Sovereign Neon Pulsar VIP 6",
        "gradientTo": "to-pink-600",
        "gradientFrom": "from-fuchsia-600",
        "isActive": true,
        "minLevel": 90,
        "badgeEmoji": "🌀"
      }
    ]
  },
  "adminUsersList": [
    {
      "vipLevel": 0,
      "coins": 1000000,
      "username": "Alina_Malik",
      "userLevel": 12,
      "fullName": "Alina Malik",
      "kycStatus": "none",
      "isVerified": false,
      "isBanned": false
    },
    {
      "vipLevel": 1,
      "coins": 1000000,
      "username": "Malik_Sheraz_40",
      "userLevel": 35,
      "fullName": "Sheraz Malik",
      "kycStatus": "approved",
      "isVerified": true,
      "isBanned": false
    },
    {
      "username": "Prince_Sehr",
      "userLevel": 24,
      "vipLevel": 3,
      "coins": 1000000,
      "kycStatus": "none",
      "isVerified": false,
      "isBanned": false,
      "fullName": ""
    },
    {
      "fullName": "Sardar Yar Khan",
      "kycStatus": "approved",
      "isVerified": true,
      "isBanned": false,
      "coins": 1000000,
      "vipLevel": 3,
      "userLevel": 50,
      "username": "Sardar_Sb_VIP"
    },
    {
      "vipLevel": 0,
      "coins": 1000000,
      "userLevel": 1,
      "username": "arooj_queen",
      "fullName": "Arooj Queen",
      "isVerified": true,
      "isBanned": false,
      "kycStatus": "approved"
    },
    {
      "isBanned": false,
      "kycStatus": "none",
      "isVerified": null,
      "fullName": "Pardais Live Official Pakistan",
      "userLevel": 1,
      "username": "pardaisliveofficial",
      "coins": 1000000,
      "vipLevel": 0
    },
    {
      "isBanned": false,
      "isVerified": true,
      "kycStatus": "approved",
      "fullName": "Soul verse Official",
      "userLevel": 1,
      "username": "soulversepk",
      "vipLevel": 0,
      "coins": 1000000
    },
    {
      "fullName": "Kashif Butt",
      "isBanned": true,
      "isVerified": false,
      "kycStatus": "rejected",
      "vipLevel": 0,
      "coins": 1000000,
      "userLevel": 4,
      "username": "toxic_viewer_9"
    },
    {
      "kycStatus": "approved",
      "isVerified": true,
      "isBanned": false,
      "fullName": "Waqas Awan",
      "userLevel": 1,
      "username": "waqasawanmalik2382",
      "coins": 1000000,
      "vipLevel": 0
    }
  ],
  "reels": [
    {
      "creator": "saif ali",
      "privacy": "public",
      "avatar": "https://lh3.googleusercontent.com/a/ACg8ocKPOUUvibO72sYkgln3jlATL7pA5-kDrEys7hveDip5w07CDTs=s96-c",
      "videoUrl": "https://2c11b4c5a1edcecac2b519c5724c4b95.r2.cloudflarestorage.com/sehrlive-reels/reels/sehr_1001/1784452725389-9icen36y.mp4",
      "song": "Pasoori - Modern Beat Mix",
      "saved": false,
      "isFollowed": false,
      "location": "Sehr Studio 🎤",
      "saves": 0,
      "comments": [],
      "liked": false,
      "createdAt": "2026-07-19T09:18:45.713Z",
      "caption": "#foryou #dhamaal",
      "uploaderId": "sehr_1001",
      "likes": 0,
      "downloads": 0,
      "commentsCount": 0,
      "shares": 0,
      "videoBg": "bg-gradient-to-tr from-[#ff007f] via-[#12121a] to-[#7b2cbf]"
    },
    {
      "location": "Lahore, Pakistan",
      "saves": 0,
      "comments": [],
      "liked": false,
      "createdAt": "2026-07-18T14:27:09.903Z",
      "isFollowed": false,
      "song": "1000127538",
      "videoUrl": "blob:https://localhost/aa0646f8-b5c6-458d-82e9-8a74099f0579",
      "saved": false,
      "creator": "saif ali",
      "privacy": "public",
      "avatar": "https://lh3.googleusercontent.com/a/ACg8ocKPOUUvibO72sYkgln3jlATL7pA5-kDrEys7hveDip5w07CDTs=s96-c",
      "videoBg": "bg-gradient-to-tr from-[#ff007f] via-[#12121a] to-[#7b2cbf]",
      "shares": 0,
      "commentsCount": 0,
      "downloads": 0,
      "caption": "#foryou #pkbattle #pakistan",
      "likes": 0
    },
    {
      "videoUrl": "https://media.sehrlive.soulverseapps.com/reels/sehr_guest_23511/1784793081584-3akfvc1t.mp4",
      "song": "1000226296",
      "objectKey": "reels/sehr_guest_23511/1784793081584-3akfvc1t.mp4",
      "saved": false,
      "creator": "Guest_23511",
      "publicUrl": "https://media.sehrlive.soulverseapps.com/reels/sehr_guest_23511/1784793081584-3akfvc1t.mp4",
      "avatar": "https://images.unsplash.com/photo-1535713875002-d1d0cf377fde?auto=format&fit=crop&w=150&h=150&q=80",
      "privacy": "public",
      "comments": [],
      "saves": 0,
      "location": "Lahore, Pakistan",
      "createdAt": "2026-07-23T07:51:21.194Z",
      "liked": false,
      "isFollowed": false,
      "downloads": 0,
      "commentsCount": 0,
      "uploaderId": "sehr_guest_23511",
      "caption": "#pakistan #pkbattle #lahore",
      "likes": 0,
      "videoBg": "bg-gradient-to-tr from-[#ff007f] via-[#12121a] to-[#7b2cbf]",
      "shares": 0,
      "mediaUrl": "https://media.sehrlive.soulverseapps.com/reels/sehr_guest_23511/1784793081584-3akfvc1t.mp4"
    },
    {
      "downloads": 0,
      "commentsCount": 0,
      "caption": "#sehrlive #singing #foryou #dhamaal",
      "uploaderId": "sehr_1001",
      "likes": 0,
      "videoBg": "bg-gradient-to-tr from-[#ff007f] via-[#12121a] to-[#7b2cbf]",
      "mediaUrl": "https://media.sehrlive.soulverseapps.com/reels/sehr_1001/1784808406397-f1a2fxrx.mp4",
      "shares": 0,
      "song": "1000220117",
      "videoUrl": "https://media.sehrlive.soulverseapps.com/reels/sehr_1001/1784808406397-f1a2fxrx.mp4",
      "objectKey": "reels/sehr_1001/1784808406397-f1a2fxrx.mp4",
      "saved": false,
      "creator": "Syed Prince Shah",
      "privacy": "public",
      "avatar": "https://api.dicebear.com/7.x/adventurer/svg?seed=SaifAli%20",
      "publicUrl": "https://media.sehrlive.soulverseapps.com/reels/sehr_1001/1784808406397-f1a2fxrx.mp4",
      "location": "Lahore, Pakistan",
      "saves": 0,
      "comments": [],
      "liked": false,
      "createdAt": "2026-07-23T12:06:46.023Z",
      "isFollowed": false
    },
    {
      "videoUrl": "blob:https://localhost/10f9b433-8a1d-4c4f-a8fa-3402e5511cb2",
      "song": "1000226296",
      "saved": false,
      "creator": "saif ali",
      "privacy": "public",
      "avatar": "https://lh3.googleusercontent.com/a/ACg8ocKPOUUvibO72sYkgln3jlATL7pA5-kDrEys7hveDip5w07CDTs=s96-c",
      "location": "Lahore, Pakistan",
      "saves": 0,
      "comments": [],
      "liked": false,
      "createdAt": "2026-07-19T07:46:07.044Z",
      "isFollowed": false,
      "downloads": 0,
      "commentsCount": 0,
      "caption": "#sehrlive #pakistan #dhamaal",
      "likes": 0,
      "videoBg": "bg-gradient-to-tr from-[#ff007f] via-[#12121a] to-[#7b2cbf]",
      "shares": 0
    },
    {
      "createdAt": "2026-07-19T08:10:42.908Z",
      "liked": false,
      "comments": [],
      "saves": 0,
      "location": "Lahore, Pakistan",
      "isFollowed": false,
      "saved": false,
      "song": "1000225716",
      "videoUrl": "blob:https://localhost/5453f9c5-60cd-4cb7-bd4a-a5d501bb9738",
      "avatar": "https://lh3.googleusercontent.com/a/ACg8ocKPOUUvibO72sYkgln3jlATL7pA5-kDrEys7hveDip5w07CDTs=s96-c",
      "privacy": "public",
      "creator": "saif ali",
      "videoBg": "bg-gradient-to-tr from-[#ff007f] via-[#12121a] to-[#7b2cbf]",
      "shares": 0,
      "commentsCount": 0,
      "downloads": 0,
      "likes": 0,
      "caption": "#sehrlive #pakistan #foryou"
    }
  ],
  "stories": [
    {
      "caption": "",
      "likes": 0,
      "replies": [
        {
          "createdAt": 1784385326651,
          "fullName": "Alina Malik",
          "avatar": "https://images.unsplash.com/photo-1544005313-94ddf0286df2?auto=format&fit=crop&w=150&q=80",
          "username": "alina_malik",
          "id": "reply_auto_1784385326651",
          "text": "Zabardast! Main abhi free ho k live ata hun! 🔥"
        },
        {
          "id": "reply_auto_owner_1784542176389",
          "text": "Hahaha, stay blessed! 🙌✨",
          "avatar": "https://lh3.googleusercontent.com/a/ACg8ocKPOUUvibO72sYkgln3jlATL7pA5-kDrEys7hveDip5w07CDTs=s96-c",
          "username": "saifkhokhar657",
          "fullName": "saif ali",
          "createdAt": 1784542176389
        },
        {
          "text": "Lots of love! 💖",
          "id": "reply_auto_owner_1784542186538",
          "username": "saifkhokhar657",
          "avatar": "https://lh3.googleusercontent.com/a/ACg8ocKPOUUvibO72sYkgln3jlATL7pA5-kDrEys7hveDip5w07CDTs=s96-c",
          "fullName": "saif ali",
          "createdAt": 1784542186538
        }
      ],
      "fullName": "saif ali",
      "type": "video",
      "username": "saifkhokhar657",
      "reactions": [
        {
          "username": "alina_malik",
          "emoji": "🙌"
        },
        {
          "username": "saifkhokhar657",
          "emoji": "❤️"
        },
        {
          "username": "guest_54443",
          "emoji": "❤️"
        },
        {
          "username": "guest_54443",
          "emoji": "🔥"
        },
        {
          "username": "guest_54443",
          "emoji": "👏"
        },
        {
          "username": "guest_54443",
          "emoji": "😮"
        },
        {
          "username": "guest_54443",
          "emoji": "😢"
        },
        {
          "username": "guest_54443",
          "emoji": "😂"
        },
        {
          "username": "guest_54443",
          "emoji": "👑"
        },
        {
          "username": "guest_54443",
          "emoji": "🙌"
        }
      ],
      "expiresAt": 1784471719177,
      "avatar": "https://lh3.googleusercontent.com/a/ACg8ocKPOUUvibO72sYkgln3jlATL7pA5-kDrEys7hveDip5w07CDTs=s96-c",
      "content": "https://assets.mixkit.co/videos/preview/mixkit-holding-a-glowing-neon-heart-41484-large.mp4",
      "id": "story_1784385319177",
      "createdAt": 1784385319177,
      "likedBy": []
    }
  ],
  "chats": [],
  "messages": [],
  "sessions": {
    "sehr_session_Sehr_User_7w6w65ak": {
      "username": "Sehr_User",
      "loginTime": "2026-07-23T11:55:41.061Z"
    },
    "sehr_session_Sehr_User_918w7dqx": {
      "username": "Sehr_User",
      "loginTime": "2026-07-23T11:59:37.513Z"
    },
    "sehr_session_Sehr_User_a7h9vixp": {
      "username": "Sehr_User",
      "loginTime": "2026-07-23T11:59:58.375Z"
    },
    "sehr_session_Sehr_User_f61btkzm": {
      "loginTime": "2026-07-24T07:48:07.229Z",
      "username": "Sehr_User"
    },
    "sehr_session_Sehr_User_k4vutgei": {
      "username": "Sehr_User",
      "loginTime": "2026-07-23T12:43:00.013Z"
    },
    "sehr_session_Sehr_User_r85pmhs2": {
      "username": "Sehr_User",
      "loginTime": "2026-07-23T12:44:50.357Z"
    },
    "sehr_session_Sehr_User_ud5o1umd": {
      "username": "Sehr_User",
      "loginTime": "2026-07-24T08:18:56.812Z"
    },
    "sehr_session_arooj_queen_i519w9po": {
      "username": "arooj_queen",
      "loginTime": "2026-07-18T08:41:11.806Z"
    },
    "sehr_session_guest_14467": {
      "loginTime": "2026-07-18T13:06:11.141Z",
      "username": "guest_14467"
    },
    "sehr_session_guest_23511": {
      "username": "guest_23511",
      "loginTime": "2026-07-20T10:08:08.792Z"
    },
    "sehr_session_guest_28397": {
      "username": "guest_28397",
      "loginTime": "2026-07-18T08:40:59.078Z"
    },
    "sehr_session_guest_38445": {
      "loginTime": "2026-07-17T12:18:50.433Z",
      "username": "guest_38445"
    },
    "sehr_session_guest_47528": {
      "username": "guest_47528",
      "loginTime": "2026-07-18T09:27:20.835Z"
    },
    "sehr_session_guest_54443": {
      "username": "guest_54443",
      "loginTime": "2026-07-20T10:08:53.326Z"
    },
    "sehr_session_guest_76509": {
      "username": "guest_76509",
      "loginTime": "2026-07-18T14:20:35.659Z"
    },
    "sehr_session_pardaisliveofficial_2l1fgmb8": {
      "loginTime": "2026-07-18T08:36:41.503Z",
      "username": "pardaisliveofficial"
    },
    "sehr_session_pardaisliveofficial_97ukvkx7": {
      "username": "pardaisliveofficial",
      "loginTime": "2026-07-18T13:07:04.321Z"
    },
    "sehr_session_pardaisliveofficial_fiz8f2lh": {
      "username": "pardaisliveofficial",
      "loginTime": "2026-07-18T09:27:51.884Z"
    },
    "sehr_session_pardaisliveofficial_n9tziniq": {
      "loginTime": "2026-07-18T09:34:39.654Z",
      "username": "pardaisliveofficial"
    },
    "sehr_session_pardaisliveofficial_o9ljuule": {
      "username": "pardaisliveofficial",
      "loginTime": "2026-07-17T12:08:06.688Z"
    },
    "sehr_session_pardaisliveofficial_w05t7r4a": {
      "loginTime": "2026-07-17T10:42:18.095Z",
      "username": "pardaisliveofficial"
    },
    "sehr_session_pardaisliveofficial_ycv6q064": {
      "loginTime": "2026-07-18T09:06:13.689Z",
      "username": "pardaisliveofficial"
    },
    "sehr_session_saifkhokhar657_3xkr06j6": {
      "username": "saifkhokhar657",
      "loginTime": "2026-07-22T08:46:18.590Z"
    },
    "sehr_session_saifkhokhar657_45qo2wtj": {
      "username": "saifkhokhar657",
      "loginTime": "2026-07-19T09:15:07.489Z"
    },
    "sehr_session_saifkhokhar657_48a0b5rr": {
      "username": "saifkhokhar657",
      "loginTime": "2026-07-22T11:03:33.907Z"
    },
    "sehr_session_saifkhokhar657_5x3zwpgv": {
      "username": "saifkhokhar657",
      "loginTime": "2026-07-18T14:24:56.619Z"
    },
    "sehr_session_saifkhokhar657_7oo8jzyo": {
      "username": "saifkhokhar657",
      "loginTime": "2026-07-22T09:59:32.440Z"
    },
    "sehr_session_saifkhokhar657_gj9ypxjw": {
      "loginTime": "2026-07-18T08:42:14.217Z",
      "username": "saifkhokhar657"
    },
    "sehr_session_saifkhokhar657_qv7g1pdp": {
      "loginTime": "2026-07-23T11:10:02.673Z",
      "username": "saifkhokhar657"
    },
    "sehr_session_saifkhokhar657_z8v7t712": {
      "loginTime": "2026-07-23T10:01:18.524Z",
      "username": "saifkhokhar657"
    },
    "sehr_session_soulversepk_mxmmerr2": {
      "loginTime": "2026-07-17T11:59:19.619Z",
      "username": "soulversepk"
    },
    "sehr_session_waqasawanmalik2382_2juw4l60": {
      "username": "waqasawanmalik2382",
      "loginTime": "2026-07-22T08:50:07.747Z"
    },
    "sehr_session_waqasawanmalik2382_3roeys6r": {
      "loginTime": "2026-07-19T01:49:20.955Z",
      "username": "waqasawanmalik2382"
    },
    "sehr_session_waqasawanmalik2382_bxyu2u6s": {
      "username": "waqasawanmalik2382",
      "loginTime": "2026-07-23T07:21:25.593Z"
    },
    "sehr_session_waqasawanmalik2382_fbq8vk9h": {
      "loginTime": "2026-07-23T08:08:40.309Z",
      "username": "waqasawanmalik2382"
    }
  },
  "otps": {},
  "agencyRequests": [],
  "purchaseRequests": [
    {
      "username": "pardaisliveofficial",
      "amountPKR": 15000000,
      "id": "PRQ-1784703858064",
      "coins": 10000000,
      "status": "Pending",
      "timestamp": "2026-07-22T07:04:18.064Z"
    }
  ],
  "coinTransactions": [],
  "approvalStatus": [],
  "adminActions": [],
  "coinSellers": []
}